<?xml version="1.0" encoding="UTF-8"?>
<Index xmlns="http://www.tso.co.uk/assets/namespace/gazetteindex" editionCode="L" page="037" pageID="https://www.thegazette.co.uk/id/London/index/year/1902/volume/2/page/037" pagePDF="https://www.thegazette.co.uk/London/index/year/1902/volume/2/page/037" pageRDF="https://www.thegazette.co.uk/London/index/year/1902/volume/2/page/037?view=linked-data" type="index" volume="2" year="1902">
  <SectionTitle>2nd Devonshire</SectionTitle>
  <ItemGroup>
    <MainItem>
      <Key>Hele</Key>
      <Title>Capt.</Title>
      <Forenames>J. C.</Forenames>
      <Text>(resigned)</Text>
      <PageNumber>5606</PageNumber>
    </MainItem>
  </ItemGroup>
  <ItemGroup>
    <MainItem>
      <Key>Herford</Key>
      <Title>Acting Chap. Rev.</Title>
      <Forenames>W. L.</Forenames>
      <Text>(resigned)</Text>
      <PageNumber>4742</PageNumber>
    </MainItem>
  </ItemGroup>
  <ItemGroup>
    <MainItem>
      <Key>Sidgwick</Key>
      <Title>Rev.</Title>
      <Forenames>J. A.</Forenames>
      <Text>(Acting Chap.)</Text>
      <PageNumber>6348</PageNumber>
    </MainItem>
    <SectionTitle>
      <Text>1st Dorsetshire</Text>
    </SectionTitle>
    <SubItem>
      <PageNumber>6744</PageNumber>
    </SubItem>
  </ItemGroup>
  <ItemGroup>
    <MainItem>
      <Key>Bagg</Key>
      <Forenames>E. W.</Forenames>
      <Text>(2nd Lieut.)</Text>
      <PageNumber>5890</PageNumber>
    </MainItem>
  </ItemGroup>
  <ItemGroup>
    <MainItem>
      <Key>Bowen</Key>
      <Title>Maj.</Title>
      <Forenames>J. H.</Forenames>
      <Text>(resigned)</Text>
      <PageNumber>7093</PageNumber>
    </MainItem>
  </ItemGroup>
  <ItemGroup>
    <MainItem>
      <Key>Reynolds</Key>
      <Forenames>E.</Forenames>
      <Text>(Maj.)</Text>
      <PageNumber>8761</PageNumber>
    </MainItem>
  </ItemGroup>
  <SectionTitle>1st Durham</SectionTitle>
  <ItemGroup>
    <MainItem>
      <Key>Elliot</Key>
      <Title>Super. 2nd Lieut.</Title>
      <Forenames>E. W.</Forenames>
      <Text>(resigned)</Text>
      <PageNumber>8846</PageNumber>
    </MainItem>
  </ItemGroup>
  <ItemGroup>
    <MainItem>
      <Key>Huggup</Key>
      <Forenames>R.</Forenames>
      <Text>(Lieut.)</Text>
      <PageNumber>7243</PageNumber>
    </MainItem>
  </ItemGroup>
  <SectionTitle>2nd Durham.</SectionTitle>
  <ItemGroup>
    <MainItem>
      <Key>Bain</Key>
      <Forenames>L. G.</Forenames>
      <Text>(Lieut.)</Text>
      <PageNumber>6570</PageNumber>
    </MainItem>
  </ItemGroup>
  <ItemGroup>
    <MainItem>
      <Key>McKenzie</Key>
      <Forenames>E. J.</Forenames>
      <Text>(Hon. Lieut.-Col.)</Text>
      <PageNumber>4515</PageNumber>
    </MainItem>
  </ItemGroup>
  <ItemGroup>
    <MainItem>
      <Key>Maddison</Key>
      <Forenames>W. Or</Forenames>
      <Text>. (Lieut.)</Text>
      <PageNumber>6570</PageNumber>
    </MainItem>
  </ItemGroup>
  <ItemGroup>
    <MainItem>
      <Key>Robsoh</Key>
      <Forenames>W. H.</Forenames>
      <Text>(2nd Lieut.)</Text>
      <PageNumber>6348</PageNumber>
    </MainItem>
  </ItemGroup>
  <ItemGroup>
    <MainItem>
      <Key>Tempest</Key>
      <Title>Maj. Lord</Title>
      <Forenames>H. L. H. V.</Forenames>
      <Text>(resigned and Hon. Lieut.-Col.)</Text>
      <PageNumber>5102</PageNumber>
    </MainItem>
  </ItemGroup>
  <SectionTitle>3rd Durham</SectionTitle>
  <ItemGroup>
    <MainItem>
      <Key>Drummond</Key>
      <Forenames>J.</Forenames>
      <Text>(Surg.-Maj.)</Text>
      <PageNumber>6151</PageNumber>
    </MainItem>
  </ItemGroup>
  <SectionTitle>' 4th Durham</SectionTitle>
  <ItemGroup>
    <MainItem>
      <Key>Guthe</Key>
      <Forenames>T. P.</Forenames>
      <Text>(Lieut.)</Text>
      <PageNumber>6348</PageNumber>
    </MainItem>
  </ItemGroup>
  <ItemGroup>
    <MainItem>
      <Key>Mudd</Key>
      <Forenames>P. A.</Forenames>
      <Text>(2nd Lieut.)</Text>
      <PageNumber>6744</PageNumber>
    </MainItem>
  </ItemGroup>
  <ItemGroup>
    <MainItem>
      <Key>Pearson</Key>
      <Title>Or.</Title>
      <Forenames>T.</Forenames>
      <Text>(Lieut.)</Text>
      <PageNumber>6348</PageNumber>
    </MainItem>
  </ItemGroup>
  <ItemGroup>
    <MainItem>
      <Key>Rickinson</Key>
      <Forenames>M.</Forenames>
      <Text>(Maj.)</Text>
      <PageNumber>ibid.</PageNumber>
    </MainItem>
  </ItemGroup>
  <ItemGroup>
    <MainItem>
      <Key>Simpson</Key>
      <Forenames>J. H.</Forenames>
      <Text>(Lieut.)..</Text>
      <PageNumber>___ ___</PageNumber>
    </MainItem>
  </ItemGroup>
  <ItemGroup>
    <MainItem>
      <Key>Strover</Key>
      <Forenames>H. W. M.</Forenames>
      <Text>(Surg.-Licut.)</Text>
      <PageNumber>5335</PageNumber>
    </MainItem>
  </ItemGroup>
  <ItemGroup>
    <MainItem>
      <Key>Wilson</Key>
      <Forenames>P.</Forenames>
      <Text>(Lieut.)</Text>
      <PageNumber>6348</PageNumber>
    </MainItem>
  </ItemGroup>
  <SectionTitle>1st Edinburgh (City)</SectionTitle>
  <ItemGroup>
    <MainItem>
      <Key>Gilruth</Key>
      <Title>Surg.</Title>
      <Text>-Maj. Or. R. (retired and Surg.-Lieut.-Col.) .,</Text>
      <PageNumber>5890</PageNumber>
    </MainItem>
  </ItemGroup>
  <ItemGroup>
    <MainItem>
      <Key>Macmillan</Key>
      <Forenames>A.</Forenames>
      <Text>(Capt.) .. ... ..</Text>
      <PageNumber>ibid.</PageNumber>
    </MainItem>
  </ItemGroup>
  <ItemGroup>
    <MainItem>
      <Key>Millar</Key>
      <Title>Capt.</Title>
      <Forenames>T. J.</Forenames>
      <Text>(resigned)</Text>
      <PageNumber>5606</PageNumber>
    </MainItem>
  </ItemGroup>
  <ItemGroup>
    <MainItem>
      <Key>Ogilvie</Key>
      <Title>Gr. (Adj.)</Title>
      <PageNumber>6744</PageNumber>
    </MainItem>
  </ItemGroup>
  <SectionTitle>1st Essex</SectionTitle>
  <ItemGroup>
    <MainItem>
      <Key>Howells</Key>
      <Forenames>H. J.</Forenames>
      <Text>(2nd Lieut.)</Text>
      <PageNumber>8846</PageNumber>
    </MainItem>
  </ItemGroup>
  <ItemGroup>
    <MainItem>
      <Key>Leake</Key>
      <Forenames>R. M.</Forenames>
      <Text>(2nd Lieut.)</Text>
      <PageNumber>7017</PageNumber>
    </MainItem>
  </ItemGroup>
  <ItemGroup>
    <MainItem>
      <Key>Partridge</Key>
      <Forenames>A. J.</Forenames>
      <Text>(2nd Lieut.) ..</Text>
      <PageNumber>ibid.</PageNumber>
    </MainItem>
  </ItemGroup>
  <ItemGroup>
    <MainItem>
      <Key>
        <KeyDitto>___ ___ ___ ___</KeyDitto>
      </Key>
      <Title>2nd Lieut.</Title>
      <Forenames>A. J.</Forenames>
      <Text>(cancellation)</Text>
      <PageNumber>8444</PageNumber>
    </MainItem>
  </ItemGroup>
  <SectionTitle>lst Fifeshire</SectionTitle>
  <ItemGroup>
    <MainItem>
      <Key>Blunt</Key>
      <Title>Capt.</Title>
      <Forenames>G.</Forenames>
      <Text>(resigned)</Text>
      <PageNumber>7538</PageNumber>
    </MainItem>
  </ItemGroup>
  <ItemGroup>
    <MainItem>
      <Key>Graham</Key>
      <Forenames>R. B.</Forenames>
      <Text>(Surg.-Maj.)</Text>
      <PageNumber>5102</PageNumber>
    </MainItem>
  </ItemGroup>
  <ItemGroup>
    <MainItem>
      <Key>Herd</Key>
      <Forenames>J. L.</Forenames>
      <Text>(Hon. Maj.)</Text>
      <PageNumber>6570</PageNumber>
    </MainItem>
  </ItemGroup>
  <ItemGroup>
    <MainItem>
      <Key>Lang</Key>
      <Forenames>P. R. S.</Forenames>
      <Text>(Hon. Col.)</Text>
      <PageNumber>6744</PageNumber>
    </MainItem>
  </ItemGroup>
  <ItemGroup>
    <MainItem>
      <Key>Linton</Key>
      <Forenames>S.</Forenames>
      <Text>(Surg.-Maj.)</Text>
      <PageNumber>5102</PageNumber>
    </MainItem>
  </ItemGroup>
  <ItemGroup>
    <MainItem>
      <Key>Moir</Key>
      <Forenames>J. W.</Forenames>
      <Text>(Surg.-Maj.) .. ..</Text>
      <PageNumber>ibid.</PageNumber>
    </MainItem>
  </ItemGroup>
  <SectionTitle>Cadet Corps (Kirkcaldy Sigh School) attached to lst Fifeshire</SectionTitle>
  <ItemGroup>
    <MainItem>
      <Key>Dawson</Key>
      <Forenames>J. M.</Forenames>
      <Text>(2nd Lieut.)</Text>
      <PageNumber>5336</PageNumber>
    </MainItem>
  </ItemGroup>
  <SectionTitle>lst Forfarshire</SectionTitle>
  <ItemGroup>
    <MainItem>
      <Key>Greig</Key>
      <Title>Lieut.</Title>
      <Forenames>J. S.</Forenames>
      <Text>(resigned)</Text>
      <PageNumber>8368</PageNumber>
    </MainItem>
  </ItemGroup>
  <ItemGroup>
    <MainItem>
      <Key>Laing</Key>
      <Forenames>D.</Forenames>
      <Text>(Maj.)</Text>
      <PageNumber>6570</PageNumber>
    </MainItem>
  </ItemGroup>
  <ItemGroup>
    <MainItem>
      <Key>Livingston</Key>
      <Forenames>E. T.</Forenames>
      <Text>(Hon. Capt.).. ..</Text>
      <PageNumber>ibid.</PageNumber>
    </MainItem>
  </ItemGroup>
  <ItemGroup>
    <MainItem>
      <Key>Malcolm</Key>
      <Forenames>K. S.</Forenames>
      <Text>(2nd Lieut.)</Text>
      <PageNumber>8444</PageNumber>
    </MainItem>
  </ItemGroup>
  <ItemGroup>
    <MainItem>
      <Key>Moncrieff</Key>
      <Title>Lieut.</Title>
      <Forenames>J.</Forenames>
      <Text>(resigned)</Text>
      <PageNumber>8368</PageNumber>
    </MainItem>
  </ItemGroup>
  <ItemGroup>
    <MainItem>
      <Key>Niven</Key>
      <Forenames>O. C.</Forenames>
      <Text>(Adj.)</Text>
      <PageNumber>8593</PageNumber>
    </MainItem>
  </ItemGroup>
  <ItemGroup>
    <MainItem>
      <Key>Rae</Key>
      <Forenames>A.F.</Forenames>
      <Text>(Lieut.)</Text>
      <PageNumber>5754</PageNumber>
    </MainItem>
  </ItemGroup>
  <ItemGroup>
    <MainItem>
      <Key>Scott</Key>
      <Title>Lieut.</Title>
      <Forenames>E. B.</Forenames>
      <Text>(resigned)</Text>
      <PageNumber>8368</PageNumber>
    </MainItem>
  </ItemGroup>
  <ItemGroup>
    <MainItem>
      <Key>
        <KeyDitto>___ ___ ___</KeyDitto>
      </Key>
      <Forenames>T.</Forenames>
      <Text>(Lieut.)</Text>
      <PageNumber>5754</PageNumber>
    </MainItem>
  </ItemGroup>
  <ItemGroup>
    <MainItem>
      <Key>Thomson</Key>
      <Title>Lieut.-Col. Comdt. and Hon. Col.</Title>
      <Forenames>W. G.</Forenames>
      <Text>(resigned)</Text>
      <PageNumber>8593</PageNumber>
    </MainItem>
  </ItemGroup>
  <SectionTitle>lst Glamorganshire</SectionTitle>
  <ItemGroup>
    <MainItem>
      <Key>Freeman</Key>
      <Forenames>B</Forenames>
      <Text>, H. (2nd Lieut.)</Text>
      <PageNumber>4515</PageNumber>
    </MainItem>
  </ItemGroup>
  <SectionTitle>2nd Glamorganshire</SectionTitle>
  <ItemGroup>
    <MainItem>
      <Key>Davies</Key>
      <Title>2nd Lieut.</Title>
      <Forenames>W. T.</Forenames>
      <Text>(resigned)</Text>
      <PageNumber>5102</PageNumber>
    </MainItem>
  </ItemGroup>
  <SectionTitle>1st Gloucestershire</SectionTitle>
  <ItemGroup>
    <MainItem>
      <Key>Austin</Key>
      <Forenames>R. L.</Forenames>
      <Text>(Lieut.)</Text>
      <PageNumber>5890</PageNumber>
    </MainItem>
  </ItemGroup>
  <ItemGroup>
    <MainItem>
      <Key>Dickinson</Key>
      <Forenames>W. J. W.</Forenames>
      <Text>(Lieut.) .. ..</Text>
      <PageNumber>ibid.</PageNumber>
    </MainItem>
  </ItemGroup>
  <ItemGroup>
    <MainItem>
      <Key>Lansdown</Key>
      <Text>[Surg.-Capt. R. G. P. (resigned) .. .. .. .. ..</Text>
      <PageNumber>ibid.</PageNumber>
    </MainItem>
  </ItemGroup>
  <ItemGroup>
    <MainItem>
      <Key>Lysaght</Key>
      <Title>Capt.</Title>
      <Forenames>S. R.</Forenames>
      <Text>(resigned)</Text>
      <PageNumber>8368</PageNumber>
    </MainItem>
  </ItemGroup>
  <ItemGroup>
    <MainItem>
      <Key>Mawer</Key>
      <Forenames>A. J.</Forenames>
      <Text>(Capt.) .. ..</Text>
      <PageNumber>ibid.</PageNumber>
    </MainItem>
  </ItemGroup>
  <ItemGroup>
    <MainItem>
      <Key>Ogilvy</Key>
      <Forenames>A.</Forenames>
      <Text>(Surg.-Lieut.)</Text>
      <PageNumber>___</PageNumber>
    </MainItem>
  </ItemGroup>
  <ItemGroup>
    <MainItem>
      <Key>
        <KeyDitto>___</KeyDitto>
      </Key>
      <Title>Capt.</Title>
      <Forenames>A.</Forenames>
      <Text>-(resigned)</Text>
      <PageNumber>___ ___</PageNumber>
    </MainItem>
  </ItemGroup>
  <ItemGroup>
    <MainItem>
      <Key>Paul</Key>
      <Forenames>A. C. S.</Forenames>
      <Text>(Lieut.)</Text>
      <PageNumber>8444</PageNumber>
    </MainItem>
  </ItemGroup>
  <ItemGroup>
    <MainItem>
      <Key>Polehampton</Key>
      <Title>Rev.</Title>
      <Forenames>T. H. S.</Forenames>
      <Text>(Acting Chap.)</Text>
      <PageNumber>8368</PageNumber>
    </MainItem>
  </ItemGroup>
  <ItemGroup>
    <MainItem>
      <Key>Spencer</Key>
      <Forenames>J. E. S.</Forenames>
      <Text>(Lieut.)</Text>
      <PageNumber>5890</PageNumber>
    </MainItem>
  </ItemGroup>
  <ItemGroup>
    <MainItem>
      <Key>Todd</Key>
      <Forenames>C. W.</Forenames>
      <Text>(Capt.)</Text>
      <PageNumber>8368</PageNumber>
    </MainItem>
  </ItemGroup>
  <ItemGroup>
    <MainItem>
      <Key>Whitwell</Key>
      <Title>Maj. and Hon. Lieut.-Col.</Title>
      <Forenames>M.</Forenames>
      <Text>, jun. (resigned)</Text>
      <PageNumber>8846</PageNumber>
    </MainItem>
  </ItemGroup>
  <SectionTitle>lst Hampshire</SectionTitle>
  <ItemGroup>
    <MainItem>
      <Key>Bayford</Key>
      <Forenames>J. K.</Forenames>
      <Text>(2nd Lieut.)</Text>
      <PageNumber>8444</PageNumber>
    </MainItem>
  </ItemGroup>
  <ItemGroup>
    <MainItem>
      <Key>Bennett</Key>
      <Title>Lieut.</Title>
      <Forenames>A. E.</Forenames>
      <Text>(resigned)</Text>
      <PageNumber>5606</PageNumber>
    </MainItem>
  </ItemGroup>
  <ItemGroup>
    <MainItem>
      <Key>Chambers</Key>
      <Text>.Surg.-Lieut. J. M. (resigned)</Text>
      <PageNumber>8368</PageNumber>
    </MainItem>
  </ItemGroup>
  <ItemGroup>
    <MainItem>
      <Key>Cook</Key>
      <Forenames>H. M.</Forenames>
      <Text>(Lieut.)</Text>
      <PageNumber>4515</PageNumber>
    </MainItem>
  </ItemGroup>
  <ItemGroup>
    <MainItem>
      <Key>Hoare</Key>
      <Forenames>K. R.</Forenames>
      <Text>(2nd Lieut.)</Text>
      <PageNumber>8444</PageNumber>
    </MainItem>
  </ItemGroup>
  <ItemGroup>
    <MainItem>
      <Key>Methven</Key>
      <Forenames>C.</Forenames>
      <Text>(Lieut.)</Text>
      <PageNumber>4515</PageNumber>
    </MainItem>
  </ItemGroup>
  <SectionTitle>2nd Hampshire</SectionTitle>
  <ItemGroup>
    <MainItem>
      <Key>Aylward</Key>
      <Title>Capt.</Title>
      <Forenames>G.</Forenames>
      <Text>(resigned and Hon. Maj.)</Text>
      <PageNumber>8444</PageNumber>
    </MainItem>
  </ItemGroup>
  <ItemGroup>
    <MainItem>
      <Key>Bassano</Key>
      <Forenames>H. F.</Forenames>
      <Text>(Surg.-Lieut.)</Text>
      <PageNumber>6570</PageNumber>
    </MainItem>
  </ItemGroup>
  <ItemGroup>
    <MainItem>
      <Key>Flowers</Key>
      <Forenames>E.</Forenames>
      <Text>(Capt.)</Text>
      <PageNumber>6024</PageNumber>
    </MainItem>
  </ItemGroup>
  <ItemGroup>
    <MainItem>
      <Key>Gant</Key>
      <Forenames>F. C.</Forenames>
      <Text>(Capt.)</Text>
      <PageNumber>ibid.</PageNumber>
    </MainItem>
  </ItemGroup>
  <ItemGroup>
    <MainItem>
      <Key>Willett</Key>
      <Title>Lieut.</Title>
      <Forenames>F. E. T.</Forenames>
      <Text>(resigned) ..</Text>
      <PageNumber>___ ___</PageNumber>
    </MainItem>
  </ItemGroup>
  <SectionTitle>The Highland</SectionTitle>
  <SectionTitle>lst Kent</SectionTitle>
  <ItemGroup>
    <MainItem>
      <Key>Bryden</Key>
      <Forenames>R. J.</Forenames>
      <Text>(Surg.-Maj.)</Text>
      <PageNumber>5102</PageNumber>
    </MainItem>
  </ItemGroup>
  <ItemGroup>
    <MainItem>
      <Key>Graham</Key>
      <Forenames>C. L.</Forenames>
      <Text>(Hon. Maj.)</Text>
      <PageNumber>8368</PageNumber>
    </MainItem>
  </ItemGroup>
  <ItemGroup>
    <MainItem>
      <Key>Smith</Key>
      <Forenames>C. L. W.</Forenames>
      <Text>(Hon. Maj.) ..</Text>
      <PageNumber>ibid.</PageNumber>
    </MainItem>
  </ItemGroup>
  <ItemGroup>
    <MainItem>
      <Key>Thomas</Key>
      <Forenames>S. E.</Forenames>
      <Text>(Lieut.)</Text>
      <PageNumber>4515</PageNumber>
    </MainItem>
  </ItemGroup>
  <ItemGroup>
    <MainItem>
      <Key>Wood</Key>
      <Title>Rev.</Title>
      <Forenames>A. H.</Forenames>
      <Text>(Acting Chap.)</Text>
      <PageNumber>5102</PageNumber>
    </MainItem>
  </ItemGroup>
  <SectionTitle>2nd, Kent</SectionTitle>
  <ItemGroup>
    <MainItem>
      <Key>Griffith</Key>
      <Forenames>F.</Forenames>
      <Text>(Hon. Maj.)..</Text>
      <PageNumber>ibid.</PageNumber>
    </MainItem>
  </ItemGroup>
  <ItemGroup>
    <MainItem>
      <Key>Tabb</Key>
      <Forenames>J. F.</Forenames>
      <Text>(Surg.-Maj.)</Text>
      <PageNumber>___</PageNumber>
    </MainItem>
  </ItemGroup>
  <SectionTitle>3rd Kent</SectionTitle>
  <ItemGroup>
    <MainItem>
      <Key>Clark</Key>
      <Forenames>H. N.</Forenames>
      <Text>(Capt)</Text>
      <PageNumber>5754</PageNumber>
    </MainItem>
  </ItemGroup>
  <ItemGroup>
    <MainItem>
      <Key>
        <KeyDitto>___ ___</KeyDitto>
      </Key>
      <Forenames>Capt</Forenames>
      <Text>, J. (resigned)</Text>
      <PageNumber>4515</PageNumber>
    </MainItem>
  </ItemGroup>
  <ItemGroup>
    <MainItem>
      <Key>de Pinna</Key>
      <Forenames>H. A. E.</Forenames>
      <Text>(Maj.)</Text>
      <PageNumber>5754</PageNumber>
    </MainItem>
  </ItemGroup>
  <ItemGroup>
    <MainItem>
      <Key>
        <KeyDitto>___ ___ ___</KeyDitto>
      </Key>
      <Title>Maj.</Title>
      <Forenames>H. A. E.</Forenames>
      <Text>(resigned and Hon. Lieut.-Col.)</Text>
      <PageNumber>8368</PageNumber>
    </MainItem>
  </ItemGroup>
  <ItemGroup>
    <MainItem>
      <Key>Hudson</Key>
      <Title>Maj. and Hon. Lieut.-Col.</Title>
      <Forenames>W. H.</Forenames>
      <Text>(resigned)</Text>
      <PageNumber>4742</PageNumber>
    </MainItem>
  </ItemGroup>
  <ItemGroup>
    <MainItem>
      <Key>Jackson</Key>
      <Forenames>F. S.</Forenames>
      <Text>(Capt.)</Text>
      <PageNumber>6744</PageNumber>
    </MainItem>
  </ItemGroup>
  <ItemGroup>
    <MainItem>
      <Key>James</Key>
      <Title>Capt.</Title>
      <Forenames>J. G. W.</Forenames>
      <Text>(resigned)</Text>
      <PageNumber>6024</PageNumber>
    </MainItem>
  </ItemGroup>
  <ItemGroup>
    <MainItem>
      <Key>Nicholls</Key>
      <Forenames>W.</Forenames>
      <Text>(Maj.)</Text>
      <PageNumber>8846</PageNumber>
    </MainItem>
  </ItemGroup>
  <ItemGroup>
    <MainItem>
      <Key>Ifott</Key>
      <Forenames>F. A.</Forenames>
      <Text>(Hon. Maj.)</Text>
      <PageNumber>7017</PageNumber>
    </MainItem>
  </ItemGroup>
  <ItemGroup>
    <MainItem>
      <Key>Odam</Key>
      <Forenames>W. T.</Forenames>
      <Text>(Capt.) ,</Text>
      <PageNumber>8846</PageNumber>
    </MainItem>
  </ItemGroup>
  <SectionTitle>Cadet Corps (attached to 3rd Kent)</SectionTitle>
  <ItemGroup>
    <MainItem>
      <Key>Pearce</Key>
      <Forenames>B. W.</Forenames>
      <Text>(Lieut.)</Text>
      <PageNumber>8444</PageNumber>
    </MainItem>
  </ItemGroup>
  <SectionTitle>lst Lanarkshire</SectionTitle>
  <ItemGroup>
    <MainItem>
      <Key>Brooke</Key>
      <Forenames>E. W. S.</Forenames>
      <Text>(Adj.)</Text>
      <PageNumber>6570</PageNumber>
    </MainItem>
  </ItemGroup>
  <ItemGroup>
    <MainItem>
      <Key>Clark</Key>
      <Forenames>J. C.</Forenames>
      <Text>(Lieut.)</Text>
      <PageNumber>5754</PageNumber>
    </MainItem>
  </ItemGroup>
  <ItemGroup>
    <MainItem>
      <Key>Costigane</Key>
      <Forenames>S. C. E.</Forenames>
      <Text>(Lieut.) .. ..</Text>
      <PageNumber>ibid.</PageNumber>
    </MainItem>
  </ItemGroup>
  <ItemGroup>
    <MainItem>
      <Key>Harrison</Key>
      <Forenames>J.</Forenames>
      <Text>(2nd Lieut.)</Text>
      <PageNumber>8761</PageNumber>
    </MainItem>
  </ItemGroup>
  <ItemGroup>
    <MainItem>
      <Key>Inglis</Key>
      <Forenames>Q</Forenames>
      <Text>,. G. (Capt.)</Text>
      <PageNumber>5754</PageNumber>
    </MainItem>
  </ItemGroup>
  <ItemGroup>
    <MainItem>
      <Key>Lightbody</Key>
      <Forenames>J.</Forenames>
      <Text>(Capt.) .. .. ..</Text>
      <PageNumber>ibid.</PageNumber>
    </MainItem>
  </ItemGroup>
  <ItemGroup>
    <MainItem>
      <Key>
        <KeyDitto>___ ___ ___ ___ ___</KeyDitto>
      </Key>
      <Forenames>W.</Forenames>
      <Text>, jun. (Maj.) .. ..</Text>
      <PageNumber>___</PageNumber>
    </MainItem>
  </ItemGroup>
  <ItemGroup>
    <MainItem>
      <Key>Russell</Key>
      <Title>Capt.</Title>
      <Forenames>J.</Forenames>
      <Text>(resigned)</Text>
      <PageNumber>8846</PageNumber>
    </MainItem>
  </ItemGroup>
  <ItemGroup>
    <MainItem>
      <Key>Spiers</Key>
      <Forenames>J.</Forenames>
      <Text>(Lieut..)</Text>
      <PageNumber>5754</PageNumber>
    </MainItem>
  </ItemGroup>
  <ItemGroup>
    <MainItem>
      <Key>Strang</Key>
      <Forenames>J. H.</Forenames>
      <Text>(Lieut.) .. .. ..</Text>
      <PageNumber>ibid.</PageNumber>
    </MainItem>
  </ItemGroup>
  <ItemGroup>
    <MainItem>
      <Key>Tinn</Key>
      <Forenames>F. G.</Forenames>
      <Text>(Lieut.)</Text>
      <PageNumber>___ ___</PageNumber>
    </MainItem>
  </ItemGroup>
  <ItemGroup>
    <MainItem>
      <Key>Wright</Key>
      <Forenames>J. L.</Forenames>
      <Text>(Lieut.)</Text>
      <PageNumber>___ ___</PageNumber>
    </MainItem>
  </ItemGroup>
  <SectionTitle>lst Lancashire</SectionTitle>
  <ItemGroup>
    <MainItem>
      <Key>German</Key>
      <Forenames>F. F.</Forenames>
      <Text>(Surg.-Capt.)</Text>
      <PageNumber>4972</PageNumber>
    </MainItem>
  </ItemGroup>
  <SectionTitle>2nd Lancashire</SectionTitle>
  <ItemGroup>
    <MainItem>
      <Key>Badcock</Key>
      <Title>Lieut.</Title>
      <Forenames>B. F.</Forenames>
      <Text>, jun. (resigned)</Text>
      <PageNumber>8846</PageNumber>
    </MainItem>
  </ItemGroup>
  <ItemGroup>
    <MainItem>
      <Key>Cohan</Key>
      <Forenames>W. M.</Forenames>
      <Text>(Lieut.)</Text>
      <PageNumber>5102</PageNumber>
    </MainItem>
  </ItemGroup>
  <ItemGroup>
    <MainItem>
      <Key>Layton</Key>
      <Title>Lieut.</Title>
      <Forenames>J. H.</Forenames>
      <Text>(resigned)</Text>
      <PageNumber>8846</PageNumber>
    </MainItem>
  </ItemGroup>
  <SectionTitle>3rd Lancashire</SectionTitle>
  <ItemGroup>
    <MainItem>
      <Key>Thorn</Key>
      <Title>Lieut-Col. and Hon. Col.</Title>
      <Forenames>W. J.</Forenames>
      <Text>(resigned)</Text>
      <PageNumber>8444</PageNumber>
    </MainItem>
  </ItemGroup>
  <ItemGroup>
    <MainItem>
      <Key>Wilkinson</Key>
      <Title>Rev.</Title>
      <Forenames>G. K.</Forenames>
      <Text>(Acting Chap.)</Text>
      <PageNumber>5469</PageNumber>
    </MainItem>
  </ItemGroup>
  <SectionTitle>4th Lancashire</SectionTitle>
  <ItemGroup>
    <MainItem>
      <Key>Briscoe</Key>
      <Forenames>G. H. T.</Forenames>
      <Text>(Lieut.)</Text>
      <PageNumber>5336</PageNumber>
    </MainItem>
  </ItemGroup>
  <ItemGroup>
    <MainItem>
      <Key>Cleaver</Key>
      <Title>Lieut.</Title>
      <Forenames>A. B.</Forenames>
      <Text>(resigned)</Text>
      <PageNumber>5606</PageNumber>
    </MainItem>
  </ItemGroup>
  <SectionTitle>oth Lancashire</SectionTitle>
  <ItemGroup>
    <MainItem>
      <Key>Bailey</Key>
      <Forenames>J.</Forenames>
      <Text>(Hon. Maj.)</Text>
      <PageNumber>4515</PageNumber>
    </MainItem>
  </ItemGroup>
  <ItemGroup>
    <MainItem>
      <Key>
        <KeyDitto>___ ___</KeyDitto>
      </Key>
      <Title>Capt. and Hon. Maj.</Title>
      <Forenames>L.</Forenames>
      <Text>(resigned) ,</Text>
      <PageNumber>8346</PageNumber>
    </MainItem>
  </ItemGroup>
  <ItemGroup>
    <MainItem>
      <Key>Lamport</Key>
      <Forenames>H. C.</Forenames>
      <Text>(Surg.-Maj.)</Text>
      <PageNumber>6151</PageNumber>
    </MainItem>
  </ItemGroup>
  <ItemGroup>
    <MainItem>
      <Key>Rigby</Key>
      <Forenames>J. A.</Forenames>
      <Text>(Surg.-Maj.)</Text>
      <PageNumber>ibid.</PageNumber>
    </MainItem>
  </ItemGroup>
  <ItemGroup>
    <MainItem>
      <Key>Oldfield</Key>
      <Forenames>L. C. L.</Forenames>
      <Text>(Adjt.)</Text>
      <PageNumber>7243</PageNumber>
    </MainItem>
  </ItemGroup>
  <ItemGroup>
    <MainItem>
      <Key>Sly</Key>
      <Title>Lieut.</Title>
      <Forenames>J.</Forenames>
      <Text>(resigned)</Text>
      <PageNumber>8761</PageNumber>
    </MainItem>
  </ItemGroup>
  <ItemGroup>
    <MainItem>
      <Key>Storey</Key>
      <Title>Lieut.</Title>
      <Forenames>R. H.</Forenames>
      <Text>(resigned)</Text>
      <PageNumber>8368</PageNumber>
    </MainItem>
  </ItemGroup>
  <SectionTitle>6th Lancashire</SectionTitle>
  <ItemGroup>
    <MainItem>
      <Key>Bird</Key>
      <Forenames>J. B.</Forenames>
      <Text>(Capt.)</Text>
      <PageNumber>4515</PageNumber>
    </MainItem>
  </ItemGroup>
  <ItemGroup>
    <MainItem>
      <Key>Brunner</Key>
      <Forenames>C. H.</Forenames>
      <Text>(Capt.)</Text>
      <PageNumber>ibid.</PageNumber>
    </MainItem>
  </ItemGroup>
  <ItemGroup>
    <MainItem>
      <Key>Gossage</Key>
      <Title>Maj. and Hon. Lieut.-Col.</Title>
      <Forenames>E. F.</Forenames>
      <Text>(resigned)</Text>
      <PageNumber>8444</PageNumber>
    </MainItem>
  </ItemGroup>
  <ItemGroup>
    <MainItem>
      <Key>Parker</Key>
      <Forenames>G. H.</Forenames>
      <Text>(Lieut.)</Text>
      <PageNumber>4515</PageNumber>
    </MainItem>
  </ItemGroup>
  <ItemGroup>
    <MainItem>
      <Key>Stead</Key>
      <Forenames>R.</Forenames>
      <Text>(2nd Lieut.)</Text>
      <PageNumber>ibid.</PageNumber>
    </MainItem>
  </ItemGroup>
  <ItemGroup>
    <MainItem>
      <Key>Tate</Key>
      <Title>Maj.</Title>
      <Forenames>E. W.</Forenames>
      <Text>(resigned)</Text>
      <PageNumber>8444</PageNumber>
    </MainItem>
  </ItemGroup>
  <SectionTitle>Sth Lancashire</SectionTitle>
  <ItemGroup>
    <MainItem>
      <Key>Phillips</Key>
      <Title>Lieut.</Title>
      <Forenames>F. E.</Forenames>
      <Text>(resigued)</Text>
      <PageNumber>8761</PageNumber>
    </MainItem>
  </ItemGroup>
  <SectionTitle>9th Lancashire</SectionTitle>
  <ItemGroup>
    <MainItem>
      <Key>Cosgrave</Key>
      <Forenames>A.</Forenames>
      <Text>(Surg.-Maj.)</Text>
      <PageNumber>4972</PageNumber>
    </MainItem>
  </ItemGroup>
  <SectionTitle>lst Lincolnshire</SectionTitle>
  <ItemGroup>
    <MainItem>
      <Key>Bannister</Key>
      <Title>Lieut.-Col. and Hon. Col.</Title>
      <Forenames>A.</Forenames>
      <Text>(retired)</Text>
      <PageNumber>7243</PageNumber>
    </MainItem>
  </ItemGroup>
  <ItemGroup>
    <MainItem>
      <Key>
        <KeyDitto>___ ___ ___ ___ ___ ___ ___ ___ ___ ___ ___ ___ ___ ___ ___ ___ ___ ___</KeyDitto>
      </Key>
      <Title>(Hon. Col.)</Title>
      <Text>.. .-</Text>
      <PageNumber>8593</PageNumber>
    </MainItem>
  </ItemGroup>
  <ItemGroup>
    <MainItem>
      <Key>Grange</Key>
      <Forenames>E. L.</Forenames>
      <Text>(Lieut.-Col. and to command)</Text>
      <PageNumber>8368</PageNumber>
    </MainItem>
  </ItemGroup>
  <ItemGroup>
    <MainItem>
      <Key>Howkins</Key>
      <Forenames>T. M.</Forenames>
      <Text>(Capt.)</Text>
      <PageNumber>8445</PageNumber>
    </MainItem>
  </ItemGroup>
  <ItemGroup>
    <MainItem>
      <Key>Tonge</Key>
      <Forenames>J.</Forenames>
      <Text>(Maj.)</Text>
      <PageNumber>ibid.</PageNumber>
    </MainItem>
  </ItemGroup>
  <SectionTitle>2nd Middlesex</SectionTitle>
  <ItemGroup>
    <MainItem>
      <Key>Dorrell</Key>
      <Title>Lieut. (Hon. Capt,)</Title>
      <Forenames>E. A.</Forenames>
      <Text>(correction)</Text>
      <PageNumber>7093</PageNumber>
    </MainItem>
  </ItemGroup>
  <ItemGroup>
    <MainItem>
      <Key>Thomas</Key>
      <Forenames>J. R.</Forenames>
      <Text>(Hon. Maj.)</Text>
      <PageNumber>6151</PageNumber>
    </MainItem>
  </ItemGroup>
  <SectionTitle>3rd Middlesex</SectionTitle>
  <ItemGroup>
    <MainItem>
      <Key>Palmer</Key>
      <Forenames>J. I.</Forenames>
      <Text>(Surg.-Maj.)</Text>
      <PageNumber>6744</PageNumber>
    </MainItem>
  </ItemGroup>
  <ItemGroup>
    <MainItem>
      <Key>Payne</Key>
      <Forenames>G.</Forenames>
      <Text>(Lieut.)</Text>
      <PageNumber>5102</PageNumber>
    </MainItem>
  </ItemGroup>
  <ItemGroup>
    <MainItem>
      <Key>Philpott</Key>
      <Forenames>H. A.</Forenames>
      <Text>(2nd Lieut.)</Text>
      <PageNumber>8444</PageNumber>
    </MainItem>
  </ItemGroup>
  <ItemGroup>
    <MainItem>
      <Key>Reed</Key>
      <Title>Lieut.</Title>
      <Forenames>T. C.</Forenames>
      <Text>(resigned)</Text>
      <PageNumber>4972</PageNumber>
    </MainItem>
  </ItemGroup>
  <ItemGroup>
    <MainItem>
      <Key>Steer</Key>
      <Title>Rev.</Title>
      <Forenames>W. H. H.</Forenames>
      <Text>(Acting Chap.)</Text>
      <PageNumber>ibid.</PageNumber>
    </MainItem>
  </ItemGroup>
  <ItemGroup>
    <MainItem>
      <Key>Tinker</Key>
      <Title>Capt.</Title>
      <Forenames>H. A.</Forenames>
      <Text>(resigned)</Text>
      <PageNumber>6744</PageNumber>
    </MainItem>
  </ItemGroup>
  <SectionTitle>lst Midlothian</SectionTitle>
  <ItemGroup>
    <MainItem>
      <Key>Findlay</Key>
      <Forenames>J. L.</Forenames>
      <Text>(Hon. Maj.)</Text>
      <PageNumber>4515</PageNumber>
    </MainItem>
  </ItemGroup>
  <ItemGroup>
    <MainItem>
      <Key>Macdonald</Key>
      <Forenames>W. B.</Forenames>
      <Text>(Surg.-Maj.)</Text>
      <PageNumber>8593</PageNumber>
    </MainItem>
  </ItemGroup>
  <ItemGroup>
    <MainItem>
      <Key>Roesler</Key>
      <Title>If.</Title>
      <Forenames>M. G.</Forenames>
      <Text>(Lieut.)</Text>
      <PageNumber>8761</PageNumber>
    </MainItem>
  </ItemGroup>
  <ItemGroup>
    <MainItem>
      <Key>Usmar</Key>
      <Forenames>Q.</Forenames>
      <Text>rmr. and Hon. Capt. G. (resigned)</Text>
      <PageNumber>8445</PageNumber>
    </MainItem>
  </ItemGroup>
  <SectionTitle>lst Monmouthshire</SectionTitle>
  <ItemGroup>
    <MainItem>
      <Key>Geen</Key>
      <Forenames>G. P.</Forenames>
      <Text>(Lieut.)</Text>
      <PageNumber>7538</PageNumber>
    </MainItem>
  </ItemGroup>
  <ItemGroup>
    <MainItem>
      <Key>Storrar</Key>
      <Forenames>D. M.</Forenames>
      <Text>(Vet.-Capt.)</Text>
      <PageNumber>6744</PageNumber>
    </MainItem>
  </ItemGroup>
  <SectionTitle>lst Newcastle-on-Tyne</SectionTitle>
  <ItemGroup>
    <MainItem>
      <Key>Bell</Key>
      <Title>Lieut.</Title>
      <Forenames>R. R.</Forenames>
      <Text>(retired)</Text>
      <PageNumber>7538</PageNumber>
    </MainItem>
  </ItemGroup>
  <ItemGroup>
    <MainItem>
      <Key>Cairns</Key>
      <Forenames>T. R.</Forenames>
      <Text>(2nd Lieut.-super.)</Text>
      <PageNumber>4972</PageNumber>
    </MainItem>
  </ItemGroup>
  <ItemGroup>
    <MainItem>
      <Key>Meikle</Key>
      <Title>Lieut.</Title>
      <Forenames>A. F. T.</Forenames>
      <Text>(absorbed into Establishment) .. .-</Text>
      <PageNumber>6153</PageNumber>
    </MainItem>
  </ItemGroup>
  <ItemGroup>
    <MainItem>
      <Key>Wilkinson</Key>
      <Title>Rev.</Title>
      <Forenames>G. K.</Forenames>
      <Text>(Acting Chap.)</Text>
      <PageNumber>5469</PageNumber>
    </MainItem>
  </ItemGroup>
  <SectionTitle>lst Norfolk</SectionTitle>
  <ItemGroup>
    <MainItem>
      <Key>Adnams</Key>
      <Forenames>E. M. V.</Forenames>
      <Text>(Hon. Lieut.-Col. )</Text>
      <PageNumber>4972</PageNumber>
    </MainItem>
  </ItemGroup>
  <ItemGroup>
    <MainItem>
      <Key>Allen</Key>
      <Forenames>S. G.</Forenames>
      <Text>(Hon. Capt.)</Text>
      <PageNumber>6024</PageNumber>
    </MainItem>
  </ItemGroup>
  <ItemGroup>
    <MainItem>
      <Key>Buckingham</Key>
      <Forenames>J.</Forenames>
      <Text>(Vet.-Lieut.)</Text>
      <PageNumber>8761</PageNumber>
    </MainItem>
  </ItemGroup>
  <ItemGroup>
    <MainItem>
      <Key>Daynes</Key>
      <Forenames>G. W.</Forenames>
      <Text>(Lieut.)</Text>
      <PageNumber>5890</PageNumber>
    </MainItem>
  </ItemGroup>
  <ItemGroup>
    <MainItem>
      <Key>Debney</Key>
      <Forenames>E. O.</Forenames>
      <Text>(Hon. Maj.)</Text>
      <PageNumber>7017</PageNumber>
    </MainItem>
  </ItemGroup>
  <ItemGroup>
    <MainItem>
      <Key>Everson</Key>
      <Forenames>J. A.</Forenames>
      <Text>(Hon. Maj.) ..</Text>
      <PageNumber>ibid.</PageNumber>
    </MainItem>
  </ItemGroup>
  <ItemGroup>
    <MainItem>
      <Key>Gabriel</Key>
      <Forenames>E. E.</Forenames>
      <Text>(Maj.)</Text>
      <PageNumber>5890</PageNumber>
    </MainItem>
  </ItemGroup>
  <ItemGroup>
    <MainItem>
      <Key>Gillett</Key>
      <Forenames>R. W.</Forenames>
      <Text>(Lieut.)</Text>
      <PageNumber>ibid.</PageNumber>
    </MainItem>
  </ItemGroup>
  <ItemGroup>
    <MainItem>
      <Key>Notley</Key>
      <Forenames>A.</Forenames>
      <Text>(Capt.)</Text>
      <PageNumber>___</PageNumber>
    </MainItem>
  </ItemGroup>
  <ItemGroup>
    <MainItem>
      <Key>Phillips</Key>
      <Forenames>W. P. F.</Forenames>
      <Text>(Lieut.)</Text>
      <PageNumber>___</PageNumber>
    </MainItem>
  </ItemGroup>
  <ItemGroup>
    <MainItem>
      <Key>Pollard</Key>
      <Title>Acting Chap. Rev.</Title>
      <Forenames>L. Or</Forenames>
      <Text>. (resigned)</Text>
      <PageNumber>4743</PageNumber>
    </MainItem>
  </ItemGroup>
  <ItemGroup>
    <MainItem>
      <Key>Ross</Key>
      <Title>Surg.</Title>
      <Text>-Lieut. A. M. (resigned)</Text>
      <PageNumber>4515</PageNumber>
    </MainItem>
  </ItemGroup>
  <ItemGroup>
    <MainItem>
      <Key>Stradbroke</Key>
      <Title>Earl</Title>
      <Text>of (Col.)</Text>
      <PageNumber>4513</PageNumber>
    </MainItem>
  </ItemGroup>
  <SectionTitle>2nd Northumberland</SectionTitle>
  <ItemGroup>
    <MainItem>
      <Key>Affleck</Key>
      <Forenames>W.</Forenames>
      <Text>(Lieut.)</Text>
      <PageNumber>6151</PageNumber>
    </MainItem>
  </ItemGroup>
  <KeyDitto>___</KeyDitto>
</Index>

