<?xml version="1.0" encoding="UTF-8"?>
<Index xmlns="http://www.tso.co.uk/assets/namespace/gazetteindex" editionCode="L" page="033" pageID="https://www.thegazette.co.uk/id/London/index/year/1905/volume/4/page/033" pagePDF="https://www.thegazette.co.uk/London/index/year/1905/volume/4/page/033" pageRDF="https://www.thegazette.co.uk/London/index/year/1905/volume/4/page/033?view=linked-data" type="index" volume="4" year="1905">
  <ItemGroup>
    <MainItem>
      <Key>Auctions</Key>
      <Forenames>Sales</Forenames>
      <Text>of Estates by, under Orders of the Court, of Chancery : Whitechapel, Black Lion Yard, Red Lion dwelling-house, &amp;c. (Braby, &amp;c. v. Stemman, . &amp;c.) ... . '</Text>
      <PageNumber>8163</PageNumber>
    </MainItem>
    <SubItem>
      <Text>Whitton Park, Hounslow-road, &amp;c, freehold building land and ground rents (Davenport v. Aldridge)</Text>
      <PageNumber>7637</PageNumber>
    </SubItem>
  </ItemGroup>
  <ItemGroup>
    <MainItem>
      <Key>Automobile</Key>
      <Text>' Wheel Company, notice of winding up .. .. .,</Text>
      <PageNumber>7027</PageNumber>
    </MainItem>
  </ItemGroup>
  <ItemGroup>
    <MainItem>
      <Key>Bahia</Key>
      <Forenames>Blanca</Forenames>
      <Text>and North-Western Railway Company, alteration of memorandum of association</Text>
      <PageNumber>9274</PageNumber>
    </MainItem>
  </ItemGroup>
  <ItemGroup>
    <MainItem>
      <Key>Bank</Key>
      <Text>of England, accumulation of dividends on Consols, £2 10s. per cent, annu ties and local loans (3 per cent.) stock</Text>
      <PageNumber>6943</PageNumber>
    </MainItem>
    <KeyDitto>___ ___ ___ ___ ___ ___</KeyDitto>
    <SubItem>
      <Text>17th „ „</Text>
      <PageNumber>6873</PageNumber>
    </SubItem>
    <SubItem>
      <Text>25th „ „</Text>
      <PageNumber>7189</PageNumber>
    </SubItem>
    <SubItem>
      <Text>8th „ „</Text>
      <PageNumber>7523</PageNumber>
    </SubItem>
    <SubItem>
      <Text>22nd „ „</Text>
      <PageNumber>8232</PageNumber>
    </SubItem>
    <SubItem>
      <Text>6th December, 1905</Text>
      <PageNumber>8822</PageNumber>
    </SubItem>
    <SubItem>
      <Text>20tb „</Text>
      <PageNumber>9194</PageNumber>
    </SubItem>
    <SubItem>
      <Text>30th „ „</Text>
      <PageNumber>6784</PageNumber>
    </SubItem>
    <SubItem>
      <Text>14th „ ,</Text>
      <PageNumber>7113</PageNumber>
    </SubItem>
    <SubItem>
      <Text>28th „ „</Text>
      <PageNumber>7436</PageNumber>
    </SubItem>
    <SubItem>
      <Text>Uth „ ,</Text>
      <PageNumber>7832</PageNumber>
    </SubItem>
    <SubItem>
      <Text>25th „ ,</Text>
      <PageNumber>8744</PageNumber>
    </SubItem>
    <SubItem>
      <Text>9th „ „</Text>
      <PageNumber>9099</PageNumber>
      <PageNumber>9192</PageNumber>
    </SubItem>
    <SubItem>
      <Text>
        <PageNumber>7612</PageNumber>
      </Text>
      <PageNumber>8924</PageNumber>
    </SubItem>
    <SubItem>
      <Text>21st October, 1905</Text>
      <PageNumber>7355</PageNumber>
    </SubItem>
    <SubItem>
      <Text>16th December, 1905</Text>
      <PageNumber>9333</PageNumber>
    </SubItem>
  </ItemGroup>
  <ItemGroup>
    <MainItem>
      <Key>Barnes</Key>
      <Text>urban district of, constant water supply</Text>
      <PageNumber>8564</PageNumber>
    </MainItem>
  </ItemGroup>
  <ItemGroup>
    <MainItem>
      <Key>Belgravia</Key>
      <Forenames>Freehold Land Company</Forenames>
      <Text>, meeting of debenture holders</Text>
      <PageNumber>9196</PageNumber>
    </MainItem>
  </ItemGroup>
  <ItemGroup>
    <MainItem>
      <Key>Birkdale</Key>
      <Text>and South port Tramways, notice to claimants for damages</Text>
      <PageNumber>8753</PageNumber>
    </MainItem>
  </ItemGroup>
  <ItemGroup>
    <MainItem>
      <Key>Board</Key>
      <Text>of Trade, applications to : Abercarn Electric Lighting</Text>
      <PageNumber>8563</PageNumber>
    </MainItem>
  </ItemGroup>
  <ItemGroup>
    <MainItem>
      <Key>Board</Key>
      <Text>of Trade, applications to : Burnham (Somerset) Pier, power to alter</Text>
      <PageNumber>7844</PageNumber>
    </MainItem>
  </ItemGroup>
  <ItemGroup>
    <MainItem>
      <Key>Board</Key>
      <Text>of Trade, applications to: . Wealdstone Electric Lighting ,</Text>
      <PageNumber>8453</PageNumber>
    </MainItem>
  </ItemGroup>
  <ItemGroup>
    <MainItem>
      <Key>Bombay</Key>
      <Forenames>Baroda</Forenames>
      <Text>, and Central India Railway Company, closure of transfer books .. .. .,</Text>
      <PageNumber>7348</PageNumber>
    </MainItem>
  </ItemGroup>
  <ItemGroup>
    <MainItem>
      <Key>Bonvalee</Key>
      <Text>et Cie, notice of winding up</Text>
      <PageNumber>7523</PageNumber>
    </MainItem>
  </ItemGroup>
  <ItemGroup>
    <MainItem>
      <Key>Brighton</Key>
      <Forenames>Coliseum</Forenames>
      <Text>, notice of winding up</Text>
      <PageNumber>6794</PageNumber>
      <PageNumber>7357</PageNumber>
    </MainItem>
  </ItemGroup>
  <ItemGroup>
    <MainItem>
      <Key>
        <KeyDitto>___ ___</KeyDitto>
      </Key>
      <Text>and Eastbourne Districts Vacuum Cleaner Company, notice of winding up</Text>
      <PageNumber>6793</PageNumber>
    </MainItem>
  </ItemGroup>
  <ItemGroup>
    <MainItem>
      <Key>Brimsdown</Key>
      <Forenames>Lead Company</Forenames>
      <Text>, reduction of capital</Text>
      <PageNumber>8932</PageNumber>
    </MainItem>
  </ItemGroup>
  <ItemGroup>
    <MainItem>
      <Key>British</Key>
      <Forenames>Compressed Air Cleaning Com-</Forenames>
      <Text>pany, notice of winding up</Text>
      <PageNumber>7027</PageNumber>
    </MainItem>
  </ItemGroup>
  <KeyDitto>___</KeyDitto>
  <ItemGroup>
    <MainItem>
      <Key>
        <KeyDitto>___ ___ ___ ___ ___ ___ ___ ___ ___ ___</KeyDitto>
      </Key>
      <PageNumber>7748</PageNumber>
    </MainItem>
  </ItemGroup>
  <ItemGroup>
    <MainItem>
      <Key>
        <KeyDitto>___ ___</KeyDitto>
      </Key>
      <Forenames>Pioneer Electric Light</Forenames>
      <Text>and Power Company of India, notice of winding up</Text>
      <PageNumber>7445</PageNumber>
    </MainItem>
  </ItemGroup>
  <ItemGroup>
    <MainItem>
      <Key>
        <KeyDitto>___ ___ ___</KeyDitto>
      </Key>
      <Forenames>Pneumatic Railway Signal Company</Forenames>
      <PageNumber>9275</PageNumber>
    </MainItem>
  </ItemGroup>
  <ItemGroup>
    <MainItem>
      <Key>
        <KeyDitto>___ ___ ___ ___ ___ ___ ___ ___ ___ ___ ___ ___ ___ ___</KeyDitto>
      </Key>
      <Text>reduction of capital</Text>
      <PageNumber>7524</PageNumber>
    </MainItem>
  </ItemGroup>
  <ItemGroup>
    <MainItem>
      <Key>
        <KeyDitto>___ ___ ___</KeyDitto>
      </Key>
      <Forenames>Seamless Rubber Company</Forenames>
      <Text>, notice of winding up</Text>
      <PageNumber>8823</PageNumber>
    </MainItem>
  </ItemGroup>
  <ItemGroup>
    <MainItem>
      <Key>Bullion</Key>
      <Text>and specie, amount of importation and exportation during the week ending : 4th October, 1905</Text>
      <PageNumber>6713</PageNumber>
    </MainItem>
    <SubItem>
      <Text>17th „ „</Text>
      <PageNumber>6872</PageNumber>
    </SubItem>
    <SubItem>
      <Text>25th „ „ .. . ..'</Text>
      <PageNumber>7188</PageNumber>
    </SubItem>
    <SubItem>
      <Text>8th ,, „</Text>
      <PageNumber>7522</PageNumber>
    </SubItem>
    <SubItem>
      <Text>22nd „</Text>
      <PageNumber>8281</PageNumber>
    </SubItem>
    <SubItem>
      <Text>6th December, 1905</Text>
      <PageNumber>8821</PageNumber>
    </SubItem>
    <SubItem>
      <Text>20th „ „</Text>
      <PageNumber>9193</PageNumber>
    </SubItem>
  </ItemGroup>
  <ItemGroup>
    <MainItem>
      <Key>Bury</Key>
      <Forenames>Rochdale</Forenames>
      <Text>, and Oldham Tramway Company, notice to debenture holders</Text>
      <PageNumber>8944</PageNumber>
    </MainItem>
  </ItemGroup>
  <ItemGroup>
    <MainItem>
      <Key>Calgary</Key>
      <Text>and Edmonton Land Company, reduction of capital .;</Text>
      <PageNumber>7190</PageNumber>
      <PageNumber>8457</PageNumber>
    </MainItem>
  </ItemGroup>
  <ItemGroup>
    <MainItem>
      <Key>Canada</Key>
      <Forenames>Company</Forenames>
      <Text>, half-yearly general court..... .. ...... i</Text>
      <PageNumber>8824</PageNumber>
    </MainItem>
  </ItemGroup>
  <ItemGroup>
    <MainItem>
      <Key>Canadian</Key>
      <Forenames>Produce Corporation</Forenames>
      <Text>, notice of winding up</Text>
      <PageNumber>7190</PageNumber>
    </MainItem>
  </ItemGroup>
  <ItemGroup>
    <MainItem>
      <Key>Cape</Key>
      <Text>of Go id Hope Government Four and a Half per Cent. Loan, annual drawing of debentures</Text>
      <PageNumber>7620</PageNumber>
    </MainItem>
  </ItemGroup>
  <ItemGroup>
    <MainItem>
      <Key>Castle</Key>
      <Forenames>General Insurance Company</Forenames>
      <Text>, notice of winding up</Text>
      <PageNumber>8574</PageNumber>
    </MainItem>
  </ItemGroup>
  <ItemGroup>
    <MainItem>
      <Key>Cave</Key>
      <Forenames>Edwards</Forenames>
      <Text>, and Co., reduction of capital</Text>
      <PageNumber>8670</PageNumber>
    </MainItem>
  </ItemGroup>
  <ItemGroup>
    <MainItem>
      <Key>Chancery</Key>
      <Text>and other Causes in which Advertisements have been inserted: Attorney-General v. Treasury Solicitor, creditors</Text>
      <PageNumber>7873</PageNumber>
      <PageNumber>8163</PageNumber>
    </MainItem>
    <SubItem>
      <Text>___ ___ ___ ___ ___ ___ ___ ___ ___ ___ ___ next of kin</Text>
      <PageNumber>7458</PageNumber>
      <PageNumber>8471</PageNumber>
    </SubItem>
    <SubItem>
      <Text>
        <PageNumber>7372</PageNumber>
      </Text>
      <PageNumber>9284</PageNumber>
    </SubItem>
    <SubItem>
      <Text>
        <PageNumber>8163</PageNumber>
        <PageNumber>7458</PageNumber>
        <PageNumber>8163</PageNumber>
      </Text>
      <PageNumber>7638</PageNumber>
    </SubItem>
    <SubItem>
      <Text>Boulter, &amp;c, v. Hughes, ' &amp;c, creditors</Text>
      <PageNumber>7541</PageNumber>
    </SubItem>
    <SubItem>
      <Text>Brown v. Young, next of kin</Text>
      <PageNumber>8943</PageNumber>
    </SubItem>
    <SubItem>
      <Text>Burgin v. Levy, next of kin</Text>
      <PageNumber>9285</PageNumber>
    </SubItem>
  </ItemGroup>
  <KeyDitto>___ ___ ___ ___ ___ ___</KeyDitto>
</Index>

